film_recommender_cg/__init__.py
film_recommender_cg/db_connector.py
film_recommender_cg/scorer.py
film_recommender_cg/trainer.py
film_recommender_cg-1.0.5.dist-info/LICENSE
film_recommender_cg-1.0.5.dist-info/METADATA
film_recommender_cg-1.0.5.dist-info/WHEEL
film_recommender_cg-1.0.5.dist-info/top_level.txt
film_recommender_cg-1.0.5.dist-info/RECORD
