Metadata-Version: 2.1
Name: film-recommender-cg
Version: 1.0.5
Summary: A Film Recommendation Engine Package
Author-email: Curtis Gribben <curtisgribben1@gmail.com>
License: Apache 2.0
Requires-Python: >=3.8
License-File: LICENSE
Requires-Dist: pandas
Requires-Dist: numpy
Requires-Dist: matplotlib
Requires-Dist: scikit-learn
Requires-Dist: scikit-surprise
Requires-Dist: pymongo
Requires-Dist: wandb
